{
  "session-id": "dt-201008141656-520A4", 
  "turns": [
    {
      "transcription-status": "transcribed", 
      "turn-index": 0, 
      "transcription": "fifty four c", 
      "audio-file": "002.raw", 
      "system-specific": {
        "act-labels": [
          {
            "source": "auto", 
            "detailed-label": "exact_match", 
            "label": true
          }, 
          {
            "source": "auto", 
            "detailed-label": "auto_not_correct", 
            "label": false
          }, 
          {
            "source": "auto", 
            "detailed-label": "auto_correct", 
            "label": true
          }, 
          {
            "source": "auto", 
            "detailed-label": "auto_not_correct", 
            "label": false
          }
        ]
      }, 
      "slu-labels": [
        {
          "source": "auto", 
          "slots": {
            "route": "54c"
          }, 
          "system-specific": "exact-match", 
          "label": true
        }, 
        {
          "source": "auto", 
          "slots": {
            "route": "14"
          }, 
          "system-specific": "auto-not-correct", 
          "label": false
        }
      ]
    }, 
    {
      "transcription-status": "transcribed", 
      "turn-index": 1, 
      "transcription": "i'm leaving from amanda and arlington", 
      "audio-file": "006.raw", 
      "system-specific": {
        "act-labels": [
          {
            "source": "auto", 
            "detailed-label": "exact_match", 
            "label": true
          }
        ]
      }, 
      "slu-labels": [
        {
          "source": "auto", 
          "slots": {
            "from.desc": "i'm leaving from amanda and arlington"
          }, 
          "system-specific": "exact-match", 
          "label": true
        }
      ]
    }, 
    {
      "transcription-status": "transcribed", 
      "turn-index": 2, 
      "transcription": "i'm what's the name of that street", 
      "audio-file": "009.raw", 
      "system-specific": {
        "act-labels": [
          {
            "source": "human", 
            "detailed-label": "not_correct", 
            "label": false
          }, 
          {
            "source": "human", 
            "detailed-label": "not_correct", 
            "label": false
          }, 
          {
            "source": "human", 
            "detailed-label": "not_correct", 
            "label": false
          }, 
          {
            "source": "human", 
            "detailed-label": "not_correct", 
            "label": false
          }, 
          {
            "source": "human", 
            "detailed-label": "not_correct", 
            "label": false
          }, 
          {
            "source": "human", 
            "detailed-label": "not_correct", 
            "label": false
          }, 
          {
            "source": "human", 
            "detailed-label": "not_correct", 
            "label": false
          }, 
          {
            "source": "human", 
            "detailed-label": "not_correct", 
            "label": false
          }, 
          {
            "source": "human", 
            "detailed-label": "not_correct", 
            "label": false
          }, 
          {
            "source": "human", 
            "detailed-label": "not_correct", 
            "label": false
          }, 
          {
            "source": "human", 
            "detailed-label": "not_correct", 
            "label": false
          }, 
          {
            "source": "human", 
            "detailed-label": "not_correct", 
            "label": false
          }, 
          {
            "source": "human", 
            "detailed-label": "not_correct", 
            "label": false
          }, 
          {
            "source": "human", 
            "detailed-label": "not_correct", 
            "label": false
          }, 
          {
            "source": "human", 
            "detailed-label": "not_correct", 
            "label": false
          }
        ]
      }, 
      "slu-labels": [
        {
          "source": "human", 
          "slots": {
            "to.desc": "i'm going to yew street"
          }, 
          "system-specific": "not-correct", 
          "label": false
        }, 
        {
          "source": "human", 
          "slots": {
            "to.desc": "i'm going to neville street"
          }, 
          "system-specific": "not-correct", 
          "label": false
        }, 
        {
          "source": "human", 
          "slots": {
            "to.desc": "i'm going to edmond street"
          }, 
          "system-specific": "not-correct", 
          "label": false
        }, 
        {
          "source": "human", 
          "slots": {
            "to.desc": "i'm going to vincent street"
          }, 
          "system-specific": "not-correct", 
          "label": false
        }, 
        {
          "source": "human", 
          "slots": {
            "to.desc": "i'm going to sarah street"
          }, 
          "system-specific": "not-correct", 
          "label": false
        }, 
        {
          "source": "human", 
          "slots": {
            "to.desc": "i'm going to bernd street"
          }, 
          "system-specific": "not-correct", 
          "label": false
        }, 
        {
          "source": "human", 
          "slots": {
            "to.desc": "i'm going to arch street"
          }, 
          "system-specific": "not-correct", 
          "label": false
        }, 
        {
          "source": "human", 
          "slots": {
            "to.desc": "i'm going to brereton street"
          }, 
          "system-specific": "not-correct", 
          "label": false
        }, 
        {
          "source": "human", 
          "slots": {
            "to.desc": "i'm going to main street"
          }, 
          "system-specific": "not-correct", 
          "label": false
        }, 
        {
          "source": "human", 
          "slots": {
            "to.desc": "i'm going to nash street"
          }, 
          "system-specific": "not-correct", 
          "label": false
        }, 
        {
          "source": "human", 
          "slots": {
            "to.desc": "i'm going to amanda street"
          }, 
          "system-specific": "not-correct", 
          "label": false
        }, 
        {
          "source": "human", 
          "slots": {
            "to.desc": "i'm going to middle street"
          }, 
          "system-specific": "not-correct", 
          "label": false
        }, 
        {
          "source": "human", 
          "slots": {
            "to.desc": "i'm going to twentieth street"
          }, 
          "system-specific": "not-correct", 
          "label": false
        }, 
        {
          "source": "human", 
          "slots": {
            "to.desc": "i'm going to mission street"
          }, 
          "system-specific": "not-correct", 
          "label": false
        }, 
        {
          "source": "human", 
          "slots": {
            "to.desc": "i'm going to mathilda street"
          }, 
          "system-specific": "not-correct", 
          "label": false
        }
      ]
    }, 
    {
      "transcription-status": "transcribed", 
      "turn-index": 3, 
      "transcription": "oakland", 
      "audio-file": "011.raw", 
      "system-specific": {
        "act-labels": [
          {
            "source": "auto", 
            "detailed-label": "exact_match", 
            "label": true
          }
        ]
      }, 
      "slu-labels": [
        {
          "source": "auto", 
          "slots": {
            "to.desc": "oakland"
          }, 
          "system-specific": "exact-match", 
          "label": true
        }
      ]
    }, 
    {
      "transcription-status": "transcribed", 
      "turn-index": 4, 
      "transcription": "yes", 
      "audio-file": "013.raw", 
      "system-specific": {
        "act-labels": [
          {
            "source": "auto", 
            "detailed-label": "auto_correct", 
            "label": true
          }, 
          {
            "source": "auto", 
            "detailed-label": "exact_match", 
            "label": true
          }, 
          {
            "source": "auto", 
            "detailed-label": "auto_not_correct", 
            "label": false
          }
        ]
      }, 
      "slu-labels": []
    }, 
    {
      "transcription-status": "transcribed", 
      "turn-index": 5, 
      "transcription": "yes", 
      "audio-file": "014.raw", 
      "system-specific": {
        "act-labels": [
          {
            "source": "auto", 
            "detailed-label": "auto_correct", 
            "label": true
          }, 
          {
            "source": "auto", 
            "detailed-label": "exact_match", 
            "label": true
          }
        ]
      }, 
      "slu-labels": []
    }, 
    {
      "transcription-status": "transcribed", 
      "turn-index": 6, 
      "transcription": "that's all", 
      "audio-file": "018.raw", 
      "system-specific": {
        "act-labels": [
          {
            "source": "human", 
            "detailed-label": "not_correct", 
            "label": false
          }
        ]
      }, 
      "slu-labels": []
    }, 
    {
      "slu-labels": [], 
      "transcription-status": "audio-not-available", 
      "audio-file": null, 
      "turn-index": 7, 
      "system-specific": {
        "act-labels": []
      }
    }
  ]
}