{
  "session-id": "dt-201008141809-270C2", 
  "turns": [
    {
      "transcription-status": "transcribed", 
      "turn-index": 0, 
      "transcription": "sixty one a", 
      "audio-file": "002.raw", 
      "system-specific": {
        "act-labels": [
          {
            "source": "auto", 
            "detailed-label": "auto_not_correct", 
            "label": false
          }, 
          {
            "source": "auto", 
            "detailed-label": "exact_match", 
            "label": true
          }, 
          {
            "source": "auto", 
            "detailed-label": "auto_not_correct", 
            "label": false
          }, 
          {
            "source": "auto", 
            "detailed-label": "auto_not_correct", 
            "label": false
          }
        ]
      }, 
      "slu-labels": [
        {
          "source": "auto", 
          "slots": {
            "route": "61a"
          }, 
          "system-specific": "exact-match", 
          "label": true
        }, 
        {
          "source": "auto", 
          "slots": {
            "route": "61c"
          }, 
          "system-specific": "auto-not-correct", 
          "label": false
        }, 
        {
          "source": "auto", 
          "slots": {
            "route": "61"
          }, 
          "system-specific": "auto-not-correct", 
          "label": false
        }, 
        {
          "source": "auto", 
          "slots": {
            "route": "61d"
          }, 
          "system-specific": "auto-not-correct", 
          "label": false
        }
      ]
    }, 
    {
      "transcription-status": "transcribed", 
      "turn-index": 1, 
      "transcription": "yes", 
      "audio-file": "004.raw", 
      "system-specific": {
        "act-labels": [
          {
            "source": "auto", 
            "detailed-label": "exact_match", 
            "label": true
          }, 
          {
            "source": "auto", 
            "detailed-label": "auto_correct", 
            "label": true
          }
        ]
      }, 
      "slu-labels": [
        {
          "source": "auto", 
          "slots": {
            "route": "61a"
          }, 
          "system-specific": "auto-expl-conf", 
          "label": true
        }
      ]
    }, 
    {
      "transcription-status": "transcribed", 
      "turn-index": 2, 
      "transcription": "downtown pittsburgh", 
      "audio-file": "005.raw", 
      "system-specific": {
        "act-labels": [
          {
            "source": "auto", 
            "detailed-label": "exact_match", 
            "label": true
          }
        ]
      }, 
      "slu-labels": [
        {
          "source": "auto", 
          "slots": {
            "from.desc": "downtown pittsburgh"
          }, 
          "system-specific": "exact-match", 
          "label": true
        }
      ]
    }, 
    {
      "transcription-status": "transcribed", 
      "turn-index": 3, 
      "transcription": "east pittsburgh", 
      "audio-file": "008.raw", 
      "system-specific": {
        "act-labels": [
          {
            "source": "auto", 
            "detailed-label": "auto_not_correct", 
            "label": false
          }, 
          {
            "source": "auto", 
            "detailed-label": "exact_match", 
            "label": true
          }, 
          {
            "source": "human", 
            "detailed-label": "not_correct", 
            "label": false
          }
        ]
      }, 
      "slu-labels": [
        {
          "source": "human", 
          "slots": {
            "to.desc": "pittsburgh"
          }, 
          "system-specific": "not-correct", 
          "label": false
        }, 
        {
          "source": "auto", 
          "slots": {
            "to.desc": "schenley park"
          }, 
          "system-specific": "auto-not-correct", 
          "label": false
        }, 
        {
          "source": "auto", 
          "slots": {
            "to.desc": "east pittsburgh"
          }, 
          "system-specific": "exact-match", 
          "label": true
        }
      ]
    }, 
    {
      "slu-labels": [
        {
          "source": "auto", 
          "slots": {
            "to.desc": "east end"
          }, 
          "system-specific": "auto-not-correct", 
          "label": false
        }, 
        {
          "source": "auto", 
          "slots": {
            "to.desc": "steps"
          }, 
          "system-specific": "auto-not-correct", 
          "label": false
        }, 
        {
          "source": "auto", 
          "slots": {
            "to.desc": "craft avenue"
          }, 
          "system-specific": "auto-not-correct", 
          "label": false
        }, 
        {
          "source": "auto", 
          "slots": {
            "to.desc": "ann street"
          }, 
          "system-specific": "auto-not-correct", 
          "label": false
        }, 
        {
          "source": "auto", 
          "slots": {
            "to.desc": "edgewood"
          }, 
          "system-specific": "auto-not-correct", 
          "label": false
        }, 
        {
          "source": "auto", 
          "slots": {
            "to.desc": "going to steps"
          }, 
          "system-specific": "auto-not-correct", 
          "label": false
        }, 
        {
          "source": "auto", 
          "slots": {
            "to.desc": "dallas ave"
          }, 
          "system-specific": "auto-not-correct", 
          "label": false
        }, 
        {
          "source": "auto", 
          "slots": {
            "to.desc": "verona street"
          }, 
          "system-specific": "auto-not-correct", 
          "label": false
        }, 
        {
          "source": "auto", 
          "slots": {
            "to.desc": "craft ave"
          }, 
          "system-specific": "auto-not-correct", 
          "label": false
        }, 
        {
          "source": "auto", 
          "slots": {
            "to.desc": "rankin"
          }, 
          "system-specific": "auto-not-correct", 
          "label": false
        }, 
        {
          "source": "auto", 
          "slots": {
            "to.desc": "gordon street"
          }, 
          "system-specific": "auto-not-correct", 
          "label": false
        }, 
        {
          "source": "auto", 
          "slots": {
            "to.desc": "oakland"
          }, 
          "system-specific": "auto-not-correct", 
          "label": false
        }, 
        {
          "source": "auto", 
          "slots": {
            "to.desc": "schenley"
          }, 
          "system-specific": "auto-not-correct", 
          "label": false
        }, 
        {
          "source": "auto", 
          "slots": {
            "to.desc": "carnegie mellon"
          }, 
          "system-specific": "auto-not-correct", 
          "label": false
        }, 
        {
          "source": "auto", 
          "slots": {
            "to.desc": "waverly"
          }, 
          "system-specific": "auto-not-correct", 
          "label": false
        }, 
        {
          "source": "auto", 
          "slots": {
            "to.desc": "dallas avenue"
          }, 
          "system-specific": "auto-not-correct", 
          "label": false
        }
      ], 
      "transcription-status": "no-speech-for-system", 
      "audio-file": "010.raw", 
      "turn-index": 4, 
      "system-specific": {
        "act-labels": [
          {
            "source": "auto", 
            "detailed-label": "auto_not_correct", 
            "label": false
          }, 
          {
            "source": "auto", 
            "detailed-label": "auto_not_correct", 
            "label": false
          }, 
          {
            "source": "auto", 
            "detailed-label": "auto_not_correct", 
            "label": false
          }, 
          {
            "source": "auto", 
            "detailed-label": "auto_not_correct", 
            "label": false
          }, 
          {
            "source": "auto", 
            "detailed-label": "auto_not_correct", 
            "label": false
          }, 
          {
            "source": "auto", 
            "detailed-label": "auto_not_correct", 
            "label": false
          }, 
          {
            "source": "auto", 
            "detailed-label": "auto_not_correct", 
            "label": false
          }, 
          {
            "source": "auto", 
            "detailed-label": "auto_not_correct", 
            "label": false
          }, 
          {
            "source": "auto", 
            "detailed-label": "auto_not_correct", 
            "label": false
          }, 
          {
            "source": "auto", 
            "detailed-label": "auto_not_correct", 
            "label": false
          }, 
          {
            "source": "auto", 
            "detailed-label": "auto_not_correct", 
            "label": false
          }, 
          {
            "source": "auto", 
            "detailed-label": "auto_not_correct", 
            "label": false
          }, 
          {
            "source": "auto", 
            "detailed-label": "auto_not_correct", 
            "label": false
          }, 
          {
            "source": "auto", 
            "detailed-label": "auto_not_correct", 
            "label": false
          }, 
          {
            "source": "auto", 
            "detailed-label": "auto_not_correct", 
            "label": false
          }, 
          {
            "source": "auto", 
            "detailed-label": "auto_not_correct", 
            "label": false
          }, 
          {
            "source": "auto", 
            "detailed-label": "auto_not_correct", 
            "label": false
          }
        ]
      }
    }, 
    {
      "slu-labels": [
        {
          "source": "auto", 
          "slots": {
            "to.desc": "east end"
          }, 
          "system-specific": "auto-not-correct", 
          "label": false
        }, 
        {
          "source": "auto", 
          "slots": {
            "to.desc": "pittsburgh"
          }, 
          "system-specific": "auto-not-correct", 
          "label": false
        }, 
        {
          "source": "auto", 
          "slots": {
            "to.desc": "to steps"
          }, 
          "system-specific": "auto-not-correct", 
          "label": false
        }, 
        {
          "source": "auto", 
          "slots": {
            "to.desc": "oakland"
          }, 
          "system-specific": "auto-not-correct", 
          "label": false
        }, 
        {
          "source": "auto", 
          "slots": {
            "to.desc": "schenley"
          }, 
          "system-specific": "auto-not-correct", 
          "label": false
        }, 
        {
          "source": "auto", 
          "slots": {
            "to.desc": "steps"
          }, 
          "system-specific": "auto-not-correct", 
          "label": false
        }
      ], 
      "transcription-status": "no-speech-for-system", 
      "audio-file": "012.raw", 
      "turn-index": 5, 
      "system-specific": {
        "act-labels": [
          {
            "source": "auto", 
            "detailed-label": "auto_not_correct", 
            "label": false
          }, 
          {
            "source": "auto", 
            "detailed-label": "auto_not_correct", 
            "label": false
          }, 
          {
            "source": "auto", 
            "detailed-label": "auto_not_correct", 
            "label": false
          }, 
          {
            "source": "auto", 
            "detailed-label": "auto_not_correct", 
            "label": false
          }, 
          {
            "source": "auto", 
            "detailed-label": "auto_not_correct", 
            "label": false
          }, 
          {
            "source": "auto", 
            "detailed-label": "auto_not_correct", 
            "label": false
          }
        ]
      }
    }, 
    {
      "slu-labels": [], 
      "transcription-status": "audio-not-available", 
      "audio-file": null, 
      "turn-index": 6, 
      "system-specific": {
        "act-labels": []
      }
    }
  ]
}