{
  "session-id": "dt-201008010001-3922C", 
  "turns": [
    {
      "slu-labels": [
        {
          "source": "auto", 
          "slots": {
            "route": "6"
          }, 
          "system-specific": "auto-not-correct", 
          "label": false
        }, 
        {
          "source": "auto", 
          "slots": {
            "route": "5"
          }, 
          "system-specific": "auto-not-correct", 
          "label": false
        }, 
        {
          "source": "auto", 
          "slots": {
            "route": "r"
          }, 
          "system-specific": "auto-not-correct", 
          "label": false
        }, 
        {
          "source": "auto", 
          "slots": {
            "route": "1"
          }, 
          "system-specific": "auto-not-correct", 
          "label": false
        }, 
        {
          "source": "auto", 
          "slots": {
            "route": "p"
          }, 
          "system-specific": "auto-not-correct", 
          "label": false
        }, 
        {
          "source": "auto", 
          "slots": {
            "route": "br"
          }, 
          "system-specific": "auto-not-correct", 
          "label": false
        }, 
        {
          "source": "auto", 
          "slots": {
            "route": "bm"
          }, 
          "system-specific": "auto-not-correct", 
          "label": false
        }, 
        {
          "source": "auto", 
          "slots": {
            "route": "g"
          }, 
          "system-specific": "auto-not-correct", 
          "label": false
        }, 
        {
          "source": "auto", 
          "slots": {
            "route": "ml"
          }, 
          "system-specific": "auto-not-correct", 
          "label": false
        }, 
        {
          "source": "auto", 
          "slots": {
            "route": "11"
          }, 
          "system-specific": "auto-not-correct", 
          "label": false
        }
      ], 
      "transcription-status": "no-speech-for-system", 
      "audio-file": "002.raw", 
      "turn-index": 0, 
      "system-specific": {
        "act-labels": [
          {
            "source": "auto", 
            "detailed-label": "auto_not_correct", 
            "label": false
          }, 
          {
            "source": "auto", 
            "detailed-label": "auto_not_correct", 
            "label": false
          }, 
          {
            "source": "auto", 
            "detailed-label": "auto_not_correct", 
            "label": false
          }, 
          {
            "source": "auto", 
            "detailed-label": "auto_not_correct", 
            "label": false
          }, 
          {
            "source": "auto", 
            "detailed-label": "auto_not_correct", 
            "label": false
          }, 
          {
            "source": "auto", 
            "detailed-label": "auto_not_correct", 
            "label": false
          }, 
          {
            "source": "auto", 
            "detailed-label": "auto_not_correct", 
            "label": false
          }, 
          {
            "source": "auto", 
            "detailed-label": "auto_not_correct", 
            "label": false
          }, 
          {
            "source": "auto", 
            "detailed-label": "auto_not_correct", 
            "label": false
          }, 
          {
            "source": "auto", 
            "detailed-label": "auto_not_correct", 
            "label": false
          }, 
          {
            "source": "auto", 
            "detailed-label": "auto_not_correct", 
            "label": false
          }, 
          {
            "source": "auto", 
            "detailed-label": "auto_not_correct", 
            "label": false
          }
        ]
      }
    }, 
    {
      "transcription-status": "transcribed", 
      "turn-index": 1, 
      "transcription": "i'm not sure", 
      "audio-file": "003.raw", 
      "system-specific": {
        "act-labels": [
          {
            "source": "auto", 
            "detailed-label": "exact_match", 
            "label": true
          }, 
          {
            "source": "auto", 
            "detailed-label": "auto_not_correct", 
            "label": false
          }
        ]
      }, 
      "slu-labels": [
        {
          "source": "auto", 
          "slots": {
            "route": "dont_know"
          }, 
          "system-specific": "exact-match", 
          "label": true
        }, 
        {
          "source": "auto", 
          "slots": {
            "route": "1"
          }, 
          "system-specific": "auto-not-correct", 
          "label": false
        }
      ]
    }, 
    {
      "transcription-status": "transcribed", 
      "turn-index": 2, 
      "transcription": "i'm not sure nigger cunt", 
      "audio-file": "006.raw", 
      "system-specific": {
        "act-labels": [
          {
            "source": "human", 
            "detailed-label": "not_correct", 
            "label": false
          }, 
          {
            "source": "human", 
            "detailed-label": "not_correct", 
            "label": false
          }, 
          {
            "source": "human", 
            "detailed-label": "not_correct", 
            "label": false
          }, 
          {
            "source": "human", 
            "detailed-label": "not_correct", 
            "label": false
          }, 
          {
            "source": "human", 
            "detailed-label": "not_correct", 
            "label": false
          }, 
          {
            "source": "human", 
            "detailed-label": "not_correct", 
            "label": false
          }, 
          {
            "source": "human", 
            "detailed-label": "not_correct", 
            "label": false
          }, 
          {
            "source": "human", 
            "detailed-label": "not_correct", 
            "label": false
          }, 
          {
            "source": "human", 
            "detailed-label": "not_correct", 
            "label": false
          }, 
          {
            "source": "human", 
            "detailed-label": "not_correct", 
            "label": false
          }, 
          {
            "source": "human", 
            "detailed-label": "not_correct", 
            "label": false
          }, 
          {
            "source": "human", 
            "detailed-label": "not_correct", 
            "label": false
          }, 
          {
            "source": "human", 
            "detailed-label": "not_correct", 
            "label": false
          }, 
          {
            "source": "human", 
            "detailed-label": "not_correct", 
            "label": false
          }, 
          {
            "source": "human", 
            "detailed-label": "not_correct", 
            "label": false
          }, 
          {
            "source": "human", 
            "detailed-label": "not_correct", 
            "label": false
          }, 
          {
            "source": "human", 
            "detailed-label": "not_correct", 
            "label": false
          }, 
          {
            "source": "human", 
            "detailed-label": "not_correct", 
            "label": false
          }, 
          {
            "source": "human", 
            "detailed-label": "not_correct", 
            "label": false
          }, 
          {
            "source": "human", 
            "detailed-label": "not_correct", 
            "label": false
          }
        ]
      }, 
      "slu-labels": [
        {
          "source": "human", 
          "slots": {
            "route": "6"
          }, 
          "system-specific": "not-correct", 
          "label": false
        }, 
        {
          "source": "human", 
          "slots": {
            "route": "5"
          }, 
          "system-specific": "not-correct", 
          "label": false
        }, 
        {
          "source": "human", 
          "slots": {
            "route": "r"
          }, 
          "system-specific": "not-correct", 
          "label": false
        }, 
        {
          "source": "human", 
          "slots": {
            "route": "1"
          }, 
          "system-specific": "not-correct", 
          "label": false
        }, 
        {
          "source": "human", 
          "slots": {
            "route": "p"
          }, 
          "system-specific": "not-correct", 
          "label": false
        }, 
        {
          "source": "human", 
          "slots": {
            "route": "y1"
          }, 
          "system-specific": "not-correct", 
          "label": false
        }, 
        {
          "source": "human", 
          "slots": {
            "route": "dont_know"
          }, 
          "system-specific": "not-correct", 
          "label": false
        }, 
        {
          "source": "human", 
          "slots": {
            "route": "br"
          }, 
          "system-specific": "not-correct", 
          "label": false
        }, 
        {
          "source": "human", 
          "slots": {
            "route": "bm"
          }, 
          "system-specific": "not-correct", 
          "label": false
        }, 
        {
          "source": "human", 
          "slots": {
            "route": "1d"
          }, 
          "system-specific": "not-correct", 
          "label": false
        }, 
        {
          "source": "human", 
          "slots": {
            "route": "g"
          }, 
          "system-specific": "not-correct", 
          "label": false
        }, 
        {
          "source": "human", 
          "slots": {
            "route": "ml"
          }, 
          "system-specific": "not-correct", 
          "label": false
        }, 
        {
          "source": "human", 
          "slots": {
            "route": "18"
          }, 
          "system-specific": "not-correct", 
          "label": false
        }, 
        {
          "source": "human", 
          "slots": {
            "route": "11"
          }, 
          "system-specific": "not-correct", 
          "label": false
        }, 
        {
          "source": "human", 
          "slots": {
            "route": "12a"
          }, 
          "system-specific": "not-correct", 
          "label": false
        }, 
        {
          "source": "human", 
          "slots": {
            "route": "g1"
          }, 
          "system-specific": "not-correct", 
          "label": false
        }, 
        {
          "source": "human", 
          "slots": {
            "route": "p10"
          }, 
          "system-specific": "not-correct", 
          "label": false
        }, 
        {
          "source": "human", 
          "slots": {
            "route": "20"
          }, 
          "system-specific": "not-correct", 
          "label": false
        }
      ]
    }, 
    {
      "slu-labels": [
        {
          "source": "auto", 
          "slots": {
            "route": "6"
          }, 
          "system-specific": "auto-not-correct", 
          "label": false
        }, 
        {
          "source": "auto", 
          "slots": {
            "route": "5"
          }, 
          "system-specific": "auto-not-correct", 
          "label": false
        }, 
        {
          "source": "auto", 
          "slots": {
            "route": "r"
          }, 
          "system-specific": "auto-not-correct", 
          "label": false
        }, 
        {
          "source": "auto", 
          "slots": {
            "route": "1"
          }, 
          "system-specific": "auto-not-correct", 
          "label": false
        }, 
        {
          "source": "auto", 
          "slots": {
            "route": "p"
          }, 
          "system-specific": "auto-not-correct", 
          "label": false
        }, 
        {
          "source": "auto", 
          "slots": {
            "route": "bm"
          }, 
          "system-specific": "auto-not-correct", 
          "label": false
        }, 
        {
          "source": "auto", 
          "slots": {
            "route": "1d"
          }, 
          "system-specific": "auto-not-correct", 
          "label": false
        }, 
        {
          "source": "auto", 
          "slots": {
            "route": "g"
          }, 
          "system-specific": "auto-not-correct", 
          "label": false
        }, 
        {
          "source": "auto", 
          "slots": {
            "route": "18"
          }, 
          "system-specific": "auto-not-correct", 
          "label": false
        }, 
        {
          "source": "auto", 
          "slots": {
            "route": "14"
          }, 
          "system-specific": "auto-not-correct", 
          "label": false
        }
      ], 
      "transcription-status": "no-speech-for-system", 
      "audio-file": "007.raw", 
      "turn-index": 3, 
      "system-specific": {
        "act-labels": [
          {
            "source": "auto", 
            "detailed-label": "auto_not_correct", 
            "label": false
          }, 
          {
            "source": "auto", 
            "detailed-label": "auto_not_correct", 
            "label": false
          }, 
          {
            "source": "auto", 
            "detailed-label": "auto_not_correct", 
            "label": false
          }, 
          {
            "source": "auto", 
            "detailed-label": "auto_not_correct", 
            "label": false
          }, 
          {
            "source": "auto", 
            "detailed-label": "auto_not_correct", 
            "label": false
          }, 
          {
            "source": "auto", 
            "detailed-label": "auto_not_correct", 
            "label": false
          }, 
          {
            "source": "auto", 
            "detailed-label": "auto_not_correct", 
            "label": false
          }, 
          {
            "source": "auto", 
            "detailed-label": "auto_not_correct", 
            "label": false
          }, 
          {
            "source": "auto", 
            "detailed-label": "auto_not_correct", 
            "label": false
          }, 
          {
            "source": "auto", 
            "detailed-label": "auto_not_correct", 
            "label": false
          }
        ]
      }
    }, 
    {
      "transcription-status": "transcribed", 
      "turn-index": 4, 
      "transcription": "i said i want your fucking number you fucking electronic nigger piece of shit", 
      "audio-file": "010.raw", 
      "system-specific": {
        "act-labels": [
          {
            "source": "human", 
            "detailed-label": "not_correct", 
            "label": false
          }, 
          {
            "source": "human", 
            "detailed-label": "not_correct", 
            "label": false
          }, 
          {
            "source": "human", 
            "detailed-label": "not_correct", 
            "label": false
          }, 
          {
            "source": "human", 
            "detailed-label": "not_correct", 
            "label": false
          }, 
          {
            "source": "human", 
            "detailed-label": "not_correct", 
            "label": false
          }, 
          {
            "source": "human", 
            "detailed-label": "not_correct", 
            "label": false
          }, 
          {
            "source": "human", 
            "detailed-label": "not_correct", 
            "label": false
          }, 
          {
            "source": "human", 
            "detailed-label": "not_correct", 
            "label": false
          }, 
          {
            "source": "human", 
            "detailed-label": "not_correct", 
            "label": false
          }, 
          {
            "source": "human", 
            "detailed-label": "not_correct", 
            "label": false
          }, 
          {
            "source": "human", 
            "detailed-label": "not_correct", 
            "label": false
          }, 
          {
            "source": "human", 
            "detailed-label": "not_correct", 
            "label": false
          }, 
          {
            "source": "human", 
            "detailed-label": "not_correct", 
            "label": false
          }, 
          {
            "source": "human", 
            "detailed-label": "not_correct", 
            "label": false
          }, 
          {
            "source": "human", 
            "detailed-label": "not_correct", 
            "label": false
          }, 
          {
            "source": "human", 
            "detailed-label": "not_correct", 
            "label": false
          }, 
          {
            "source": "human", 
            "detailed-label": "not_correct", 
            "label": false
          }, 
          {
            "source": "human", 
            "detailed-label": "not_correct", 
            "label": false
          }, 
          {
            "source": "human", 
            "detailed-label": "not_correct", 
            "label": false
          }, 
          {
            "source": "human", 
            "detailed-label": "not_correct", 
            "label": false
          }
        ]
      }, 
      "slu-labels": [
        {
          "source": "human", 
          "slots": {
            "route": "6"
          }, 
          "system-specific": "not-correct", 
          "label": false
        }, 
        {
          "source": "human", 
          "slots": {
            "route": "5"
          }, 
          "system-specific": "not-correct", 
          "label": false
        }, 
        {
          "source": "human", 
          "slots": {
            "route": "6a"
          }, 
          "system-specific": "not-correct", 
          "label": false
        }, 
        {
          "source": "human", 
          "slots": {
            "route": "red"
          }, 
          "system-specific": "not-correct", 
          "label": false
        }, 
        {
          "source": "human", 
          "slots": {
            "route": "r"
          }, 
          "system-specific": "not-correct", 
          "label": false
        }, 
        {
          "source": "human", 
          "slots": {
            "route": "1"
          }, 
          "system-specific": "not-correct", 
          "label": false
        }, 
        {
          "source": "human", 
          "slots": {
            "route": "p"
          }, 
          "system-specific": "not-correct", 
          "label": false
        }, 
        {
          "source": "human", 
          "slots": {
            "route": "p10"
          }, 
          "system-specific": "not-correct", 
          "label": false
        }, 
        {
          "source": "human", 
          "slots": {
            "route": "1f"
          }, 
          "system-specific": "not-correct", 
          "label": false
        }, 
        {
          "source": "human", 
          "slots": {
            "route": "gc"
          }, 
          "system-specific": "not-correct", 
          "label": false
        }, 
        {
          "source": "human", 
          "slots": {
            "route": "pg"
          }, 
          "system-specific": "not-correct", 
          "label": false
        }, 
        {
          "source": "human", 
          "slots": {
            "route": "g"
          }, 
          "system-specific": "not-correct", 
          "label": false
        }, 
        {
          "source": "human", 
          "slots": {
            "route": "6d"
          }, 
          "system-specific": "not-correct", 
          "label": false
        }, 
        {
          "source": "human", 
          "slots": {
            "route": "20"
          }, 
          "system-specific": "not-correct", 
          "label": false
        }, 
        {
          "source": "human", 
          "slots": {
            "route": "6c"
          }, 
          "system-specific": "not-correct", 
          "label": false
        }, 
        {
          "source": "human", 
          "slots": {
            "route": "1d"
          }, 
          "system-specific": "not-correct", 
          "label": false
        }, 
        {
          "source": "human", 
          "slots": {
            "route": "g1"
          }, 
          "system-specific": "not-correct", 
          "label": false
        }, 
        {
          "source": "human", 
          "slots": {
            "route": "g3"
          }, 
          "system-specific": "not-correct", 
          "label": false
        }, 
        {
          "source": "human", 
          "slots": {
            "route": "g2"
          }, 
          "system-specific": "not-correct", 
          "label": false
        }
      ]
    }, 
    {
      "slu-labels": [
        {
          "source": "auto", 
          "slots": {
            "route": "6"
          }, 
          "system-specific": "auto-not-correct", 
          "label": false
        }, 
        {
          "source": "auto", 
          "slots": {
            "route": "5"
          }, 
          "system-specific": "auto-not-correct", 
          "label": false
        }, 
        {
          "source": "auto", 
          "slots": {
            "route": "r"
          }, 
          "system-specific": "auto-not-correct", 
          "label": false
        }, 
        {
          "source": "auto", 
          "slots": {
            "route": "1"
          }, 
          "system-specific": "auto-not-correct", 
          "label": false
        }, 
        {
          "source": "auto", 
          "slots": {
            "route": "p"
          }, 
          "system-specific": "auto-not-correct", 
          "label": false
        }, 
        {
          "source": "auto", 
          "slots": {
            "route": "60"
          }, 
          "system-specific": "auto-not-correct", 
          "label": false
        }, 
        {
          "source": "auto", 
          "slots": {
            "route": "bm"
          }, 
          "system-specific": "auto-not-correct", 
          "label": false
        }, 
        {
          "source": "auto", 
          "slots": {
            "route": "g"
          }, 
          "system-specific": "auto-not-correct", 
          "label": false
        }, 
        {
          "source": "auto", 
          "slots": {
            "route": "18"
          }, 
          "system-specific": "auto-not-correct", 
          "label": false
        }, 
        {
          "source": "auto", 
          "slots": {
            "route": "20"
          }, 
          "system-specific": "auto-not-correct", 
          "label": false
        }, 
        {
          "source": "auto", 
          "slots": {
            "route": "14"
          }, 
          "system-specific": "auto-not-correct", 
          "label": false
        }
      ], 
      "transcription-status": "no-speech-for-system", 
      "audio-file": "011.raw", 
      "turn-index": 5, 
      "system-specific": {
        "act-labels": [
          {
            "source": "auto", 
            "detailed-label": "auto_not_correct", 
            "label": false
          }, 
          {
            "source": "auto", 
            "detailed-label": "auto_not_correct", 
            "label": false
          }, 
          {
            "source": "auto", 
            "detailed-label": "auto_not_correct", 
            "label": false
          }, 
          {
            "source": "auto", 
            "detailed-label": "auto_not_correct", 
            "label": false
          }, 
          {
            "source": "auto", 
            "detailed-label": "auto_not_correct", 
            "label": false
          }, 
          {
            "source": "auto", 
            "detailed-label": "auto_not_correct", 
            "label": false
          }, 
          {
            "source": "auto", 
            "detailed-label": "auto_not_correct", 
            "label": false
          }, 
          {
            "source": "auto", 
            "detailed-label": "auto_not_correct", 
            "label": false
          }, 
          {
            "source": "auto", 
            "detailed-label": "auto_not_correct", 
            "label": false
          }, 
          {
            "source": "auto", 
            "detailed-label": "auto_not_correct", 
            "label": false
          }, 
          {
            "source": "auto", 
            "detailed-label": "auto_not_correct", 
            "label": false
          }, 
          {
            "source": "auto", 
            "detailed-label": "auto_not_correct", 
            "label": false
          }, 
          {
            "source": "auto", 
            "detailed-label": "auto_not_correct", 
            "label": false
          }, 
          {
            "source": "auto", 
            "detailed-label": "auto_not_correct", 
            "label": false
          }
        ]
      }
    }, 
    {
      "transcription-status": "transcribed", 
      "turn-index": 6, 
      "transcription": "nigger", 
      "audio-file": "012.raw", 
      "system-specific": {
        "act-labels": [
          {
            "source": "human", 
            "detailed-label": "not_correct", 
            "label": false
          }, 
          {
            "source": "human", 
            "detailed-label": "not_correct", 
            "label": false
          }, 
          {
            "source": "human", 
            "detailed-label": "not_correct", 
            "label": false
          }, 
          {
            "source": "human", 
            "detailed-label": "not_correct", 
            "label": false
          }, 
          {
            "source": "human", 
            "detailed-label": "not_correct", 
            "label": false
          }, 
          {
            "source": "human", 
            "detailed-label": "not_correct", 
            "label": false
          }, 
          {
            "source": "human", 
            "detailed-label": "not_correct", 
            "label": false
          }, 
          {
            "source": "human", 
            "detailed-label": "not_correct", 
            "label": false
          }, 
          {
            "source": "human", 
            "detailed-label": "not_correct", 
            "label": false
          }, 
          {
            "source": "human", 
            "detailed-label": "not_correct", 
            "label": false
          }, 
          {
            "source": "human", 
            "detailed-label": "not_correct", 
            "label": false
          }, 
          {
            "source": "human", 
            "detailed-label": "not_correct", 
            "label": false
          }, 
          {
            "source": "human", 
            "detailed-label": "not_correct", 
            "label": false
          }, 
          {
            "source": "human", 
            "detailed-label": "not_correct", 
            "label": false
          }, 
          {
            "source": "human", 
            "detailed-label": "not_correct", 
            "label": false
          }, 
          {
            "source": "human", 
            "detailed-label": "not_correct", 
            "label": false
          }, 
          {
            "source": "human", 
            "detailed-label": "not_correct", 
            "label": false
          }, 
          {
            "source": "human", 
            "detailed-label": "not_correct", 
            "label": false
          }, 
          {
            "source": "human", 
            "detailed-label": "not_correct", 
            "label": false
          }, 
          {
            "source": "human", 
            "detailed-label": "not_correct", 
            "label": false
          }, 
          {
            "source": "human", 
            "detailed-label": "not_correct", 
            "label": false
          }, 
          {
            "source": "human", 
            "detailed-label": "not_correct", 
            "label": false
          }, 
          {
            "source": "human", 
            "detailed-label": "not_correct", 
            "label": false
          }, 
          {
            "source": "human", 
            "detailed-label": "not_correct", 
            "label": false
          }, 
          {
            "source": "human", 
            "detailed-label": "not_correct", 
            "label": false
          }, 
          {
            "source": "human", 
            "detailed-label": "not_correct", 
            "label": false
          }, 
          {
            "source": "human", 
            "detailed-label": "not_correct", 
            "label": false
          }, 
          {
            "source": "human", 
            "detailed-label": "not_correct", 
            "label": false
          }, 
          {
            "source": "human", 
            "detailed-label": "not_correct", 
            "label": false
          }, 
          {
            "source": "human", 
            "detailed-label": "not_correct", 
            "label": false
          }, 
          {
            "source": "human", 
            "detailed-label": "not_correct", 
            "label": false
          }
        ]
      }, 
      "slu-labels": [
        {
          "source": "human", 
          "slots": {
            "route": "o5"
          }, 
          "system-specific": "not-correct", 
          "label": false
        }, 
        {
          "source": "human", 
          "slots": {
            "route": "g3"
          }, 
          "system-specific": "not-correct", 
          "label": false
        }, 
        {
          "source": "human", 
          "slots": {
            "route": "18"
          }, 
          "system-specific": "not-correct", 
          "label": false
        }, 
        {
          "source": "human", 
          "slots": {
            "route": "6c"
          }, 
          "system-specific": "not-correct", 
          "label": false
        }, 
        {
          "source": "human", 
          "slots": {
            "route": "11"
          }, 
          "system-specific": "not-correct", 
          "label": false
        }, 
        {
          "source": "human", 
          "slots": {
            "route": "6a"
          }, 
          "system-specific": "not-correct", 
          "label": false
        }, 
        {
          "source": "human", 
          "slots": {
            "route": "16"
          }, 
          "system-specific": "not-correct", 
          "label": false
        }, 
        {
          "source": "human", 
          "slots": {
            "route": "15"
          }, 
          "system-specific": "not-correct", 
          "label": false
        }, 
        {
          "source": "human", 
          "slots": {
            "route": "6"
          }, 
          "system-specific": "not-correct", 
          "label": false
        }, 
        {
          "source": "human", 
          "slots": {
            "route": "5"
          }, 
          "system-specific": "not-correct", 
          "label": false
        }, 
        {
          "source": "human", 
          "slots": {
            "route": "12a"
          }, 
          "system-specific": "not-correct", 
          "label": false
        }, 
        {
          "source": "human", 
          "slots": {
            "route": "1"
          }, 
          "system-specific": "not-correct", 
          "label": false
        }, 
        {
          "source": "human", 
          "slots": {
            "route": "br"
          }, 
          "system-specific": "not-correct", 
          "label": false
        }, 
        {
          "source": "human", 
          "slots": {
            "route": "bm"
          }, 
          "system-specific": "not-correct", 
          "label": false
        }, 
        {
          "source": "human", 
          "slots": {
            "route": "6d"
          }, 
          "system-specific": "not-correct", 
          "label": false
        }, 
        {
          "source": "human", 
          "slots": {
            "route": "p10"
          }, 
          "system-specific": "not-correct", 
          "label": false
        }, 
        {
          "source": "human", 
          "slots": {
            "route": "y1"
          }, 
          "system-specific": "not-correct", 
          "label": false
        }, 
        {
          "source": "human", 
          "slots": {
            "route": "60"
          }, 
          "system-specific": "not-correct", 
          "label": false
        }, 
        {
          "source": "human", 
          "slots": {
            "route": "p11"
          }, 
          "system-specific": "not-correct", 
          "label": false
        }, 
        {
          "source": "human", 
          "slots": {
            "route": "1f"
          }, 
          "system-specific": "not-correct", 
          "label": false
        }, 
        {
          "source": "human", 
          "slots": {
            "route": "gc"
          }, 
          "system-specific": "not-correct", 
          "label": false
        }, 
        {
          "source": "human", 
          "slots": {
            "route": "1d"
          }, 
          "system-specific": "not-correct", 
          "label": false
        }, 
        {
          "source": "human", 
          "slots": {
            "route": "ml"
          }, 
          "system-specific": "not-correct", 
          "label": false
        }, 
        {
          "source": "human", 
          "slots": {
            "route": "pg"
          }, 
          "system-specific": "not-correct", 
          "label": false
        }, 
        {
          "source": "human", 
          "slots": {
            "route": "20"
          }, 
          "system-specific": "not-correct", 
          "label": false
        }, 
        {
          "source": "human", 
          "slots": {
            "route": "w"
          }, 
          "system-specific": "not-correct", 
          "label": false
        }, 
        {
          "source": "human", 
          "slots": {
            "route": "r"
          }, 
          "system-specific": "not-correct", 
          "label": false
        }, 
        {
          "source": "human", 
          "slots": {
            "route": "p"
          }, 
          "system-specific": "not-correct", 
          "label": false
        }, 
        {
          "source": "human", 
          "slots": {
            "route": "g"
          }, 
          "system-specific": "not-correct", 
          "label": false
        }
      ]
    }, 
    {
      "transcription-status": "transcribed", 
      "turn-index": 7, 
      "transcription": "nigger", 
      "audio-file": "014.raw", 
      "system-specific": {
        "act-labels": [
          {
            "source": "human", 
            "detailed-label": "not_correct", 
            "label": false
          }, 
          {
            "source": "human", 
            "detailed-label": "not_correct", 
            "label": false
          }, 
          {
            "source": "human", 
            "detailed-label": "not_correct", 
            "label": false
          }, 
          {
            "source": "human", 
            "detailed-label": "not_correct", 
            "label": false
          }, 
          {
            "source": "human", 
            "detailed-label": "not_correct", 
            "label": false
          }, 
          {
            "source": "human", 
            "detailed-label": "not_correct", 
            "label": false
          }, 
          {
            "source": "human", 
            "detailed-label": "not_correct", 
            "label": false
          }, 
          {
            "source": "human", 
            "detailed-label": "not_correct", 
            "label": false
          }, 
          {
            "source": "human", 
            "detailed-label": "not_correct", 
            "label": false
          }
        ]
      }, 
      "slu-labels": [
        {
          "source": "human", 
          "slots": {
            "route": "6"
          }, 
          "system-specific": "not-correct", 
          "label": false
        }, 
        {
          "source": "human", 
          "slots": {
            "route": "5"
          }, 
          "system-specific": "not-correct", 
          "label": false
        }, 
        {
          "source": "human", 
          "slots": {
            "route": "r"
          }, 
          "system-specific": "not-correct", 
          "label": false
        }, 
        {
          "source": "human", 
          "slots": {
            "route": "1"
          }, 
          "system-specific": "not-correct", 
          "label": false
        }, 
        {
          "source": "human", 
          "slots": {
            "route": "p"
          }, 
          "system-specific": "not-correct", 
          "label": false
        }, 
        {
          "source": "human", 
          "slots": {
            "route": "br"
          }, 
          "system-specific": "not-correct", 
          "label": false
        }, 
        {
          "source": "human", 
          "slots": {
            "route": "bm"
          }, 
          "system-specific": "not-correct", 
          "label": false
        }, 
        {
          "source": "human", 
          "slots": {
            "route": "g"
          }, 
          "system-specific": "not-correct", 
          "label": false
        }, 
        {
          "source": "human", 
          "slots": {
            "route": "ml"
          }, 
          "system-specific": "not-correct", 
          "label": false
        }
      ]
    }, 
    {
      "transcription-status": "transcribed", 
      "turn-index": 8, 
      "transcription": "i'm not sure not sure not fucking nigger sure shut the fuck up you electronic cunt", 
      "audio-file": "016.raw", 
      "system-specific": {
        "act-labels": [
          {
            "source": "human", 
            "detailed-label": "not_correct", 
            "label": false
          }, 
          {
            "source": "human", 
            "detailed-label": "not_correct", 
            "label": false
          }, 
          {
            "source": "human", 
            "detailed-label": "not_correct", 
            "label": false
          }, 
          {
            "source": "human", 
            "detailed-label": "not_correct", 
            "label": false
          }, 
          {
            "source": "human", 
            "detailed-label": "not_correct", 
            "label": false
          }, 
          {
            "source": "human", 
            "detailed-label": "not_correct", 
            "label": false
          }, 
          {
            "source": "human", 
            "detailed-label": "not_correct", 
            "label": false
          }, 
          {
            "source": "human", 
            "detailed-label": "not_correct", 
            "label": false
          }, 
          {
            "source": "human", 
            "detailed-label": "not_correct", 
            "label": false
          }, 
          {
            "source": "human", 
            "detailed-label": "not_correct", 
            "label": false
          }, 
          {
            "source": "human", 
            "detailed-label": "not_correct", 
            "label": false
          }, 
          {
            "source": "human", 
            "detailed-label": "not_correct", 
            "label": false
          }
        ]
      }, 
      "slu-labels": [
        {
          "source": "human", 
          "slots": {
            "route": "6"
          }, 
          "system-specific": "not-correct", 
          "label": false
        }, 
        {
          "source": "human", 
          "slots": {
            "route": "5"
          }, 
          "system-specific": "not-correct", 
          "label": false
        }, 
        {
          "source": "human", 
          "slots": {
            "route": "r"
          }, 
          "system-specific": "not-correct", 
          "label": false
        }, 
        {
          "source": "human", 
          "slots": {
            "route": "1"
          }, 
          "system-specific": "not-correct", 
          "label": false
        }, 
        {
          "source": "human", 
          "slots": {
            "route": "p"
          }, 
          "system-specific": "not-correct", 
          "label": false
        }, 
        {
          "source": "human", 
          "slots": {
            "route": "60"
          }, 
          "system-specific": "not-correct", 
          "label": false
        }, 
        {
          "source": "human", 
          "slots": {
            "route": "bm"
          }, 
          "system-specific": "not-correct", 
          "label": false
        }, 
        {
          "source": "human", 
          "slots": {
            "route": "g"
          }, 
          "system-specific": "not-correct", 
          "label": false
        }, 
        {
          "source": "human", 
          "slots": {
            "route": "ml"
          }, 
          "system-specific": "not-correct", 
          "label": false
        }, 
        {
          "source": "human", 
          "slots": {
            "route": "g3"
          }, 
          "system-specific": "not-correct", 
          "label": false
        }, 
        {
          "source": "human", 
          "slots": {
            "route": "20"
          }, 
          "system-specific": "not-correct", 
          "label": false
        }
      ]
    }, 
    {
      "slu-labels": [
        {
          "source": "auto", 
          "slots": {
            "route": "6"
          }, 
          "system-specific": "auto-not-correct", 
          "label": false
        }, 
        {
          "source": "auto", 
          "slots": {
            "route": "5"
          }, 
          "system-specific": "auto-not-correct", 
          "label": false
        }, 
        {
          "source": "auto", 
          "slots": {
            "route": "r"
          }, 
          "system-specific": "auto-not-correct", 
          "label": false
        }, 
        {
          "source": "auto", 
          "slots": {
            "route": "1"
          }, 
          "system-specific": "auto-not-correct", 
          "label": false
        }, 
        {
          "source": "auto", 
          "slots": {
            "route": "p"
          }, 
          "system-specific": "auto-not-correct", 
          "label": false
        }, 
        {
          "source": "auto", 
          "slots": {
            "route": "bm"
          }, 
          "system-specific": "auto-not-correct", 
          "label": false
        }, 
        {
          "source": "auto", 
          "slots": {
            "route": "g"
          }, 
          "system-specific": "auto-not-correct", 
          "label": false
        }, 
        {
          "source": "auto", 
          "slots": {
            "route": "ml"
          }, 
          "system-specific": "auto-not-correct", 
          "label": false
        }, 
        {
          "source": "auto", 
          "slots": {
            "route": "g1"
          }, 
          "system-specific": "auto-not-correct", 
          "label": false
        }, 
        {
          "source": "auto", 
          "slots": {
            "route": "20"
          }, 
          "system-specific": "auto-not-correct", 
          "label": false
        }
      ], 
      "transcription-status": "no-speech-for-system", 
      "audio-file": "017.raw", 
      "turn-index": 9, 
      "system-specific": {
        "act-labels": [
          {
            "source": "auto", 
            "detailed-label": "auto_not_correct", 
            "label": false
          }, 
          {
            "source": "auto", 
            "detailed-label": "auto_not_correct", 
            "label": false
          }, 
          {
            "source": "auto", 
            "detailed-label": "auto_not_correct", 
            "label": false
          }, 
          {
            "source": "auto", 
            "detailed-label": "auto_not_correct", 
            "label": false
          }, 
          {
            "source": "auto", 
            "detailed-label": "auto_not_correct", 
            "label": false
          }, 
          {
            "source": "auto", 
            "detailed-label": "auto_not_correct", 
            "label": false
          }, 
          {
            "source": "auto", 
            "detailed-label": "auto_not_correct", 
            "label": false
          }, 
          {
            "source": "auto", 
            "detailed-label": "auto_not_correct", 
            "label": false
          }, 
          {
            "source": "auto", 
            "detailed-label": "auto_not_correct", 
            "label": false
          }, 
          {
            "source": "auto", 
            "detailed-label": "auto_not_correct", 
            "label": false
          }, 
          {
            "source": "auto", 
            "detailed-label": "auto_not_correct", 
            "label": false
          }, 
          {
            "source": "auto", 
            "detailed-label": "auto_not_correct", 
            "label": false
          }
        ]
      }
    }, 
    {
      "slu-labels": [
        {
          "source": "auto", 
          "slots": {
            "route": "6"
          }, 
          "system-specific": "auto-not-correct", 
          "label": false
        }, 
        {
          "source": "auto", 
          "slots": {
            "route": "5"
          }, 
          "system-specific": "auto-not-correct", 
          "label": false
        }, 
        {
          "source": "auto", 
          "slots": {
            "route": "bm"
          }, 
          "system-specific": "auto-not-correct", 
          "label": false
        }, 
        {
          "source": "auto", 
          "slots": {
            "route": "r"
          }, 
          "system-specific": "auto-not-correct", 
          "label": false
        }, 
        {
          "source": "auto", 
          "slots": {
            "route": "1"
          }, 
          "system-specific": "auto-not-correct", 
          "label": false
        }, 
        {
          "source": "auto", 
          "slots": {
            "route": "p"
          }, 
          "system-specific": "auto-not-correct", 
          "label": false
        }, 
        {
          "source": "auto", 
          "slots": {
            "route": "br"
          }, 
          "system-specific": "auto-not-correct", 
          "label": false
        }, 
        {
          "source": "auto", 
          "slots": {
            "route": "y1"
          }, 
          "system-specific": "auto-not-correct", 
          "label": false
        }, 
        {
          "source": "auto", 
          "slots": {
            "route": "g"
          }, 
          "system-specific": "auto-not-correct", 
          "label": false
        }, 
        {
          "source": "auto", 
          "slots": {
            "route": "ml"
          }, 
          "system-specific": "auto-not-correct", 
          "label": false
        }, 
        {
          "source": "auto", 
          "slots": {
            "route": "20"
          }, 
          "system-specific": "auto-not-correct", 
          "label": false
        }
      ], 
      "transcription-status": "no-speech-for-system", 
      "audio-file": "018.raw", 
      "turn-index": 10, 
      "system-specific": {
        "act-labels": [
          {
            "source": "auto", 
            "detailed-label": "auto_not_correct", 
            "label": false
          }, 
          {
            "source": "auto", 
            "detailed-label": "auto_not_correct", 
            "label": false
          }, 
          {
            "source": "auto", 
            "detailed-label": "auto_not_correct", 
            "label": false
          }, 
          {
            "source": "auto", 
            "detailed-label": "auto_not_correct", 
            "label": false
          }, 
          {
            "source": "auto", 
            "detailed-label": "auto_not_correct", 
            "label": false
          }, 
          {
            "source": "auto", 
            "detailed-label": "auto_not_correct", 
            "label": false
          }, 
          {
            "source": "auto", 
            "detailed-label": "auto_not_correct", 
            "label": false
          }, 
          {
            "source": "auto", 
            "detailed-label": "auto_not_correct", 
            "label": false
          }, 
          {
            "source": "auto", 
            "detailed-label": "auto_not_correct", 
            "label": false
          }, 
          {
            "source": "auto", 
            "detailed-label": "auto_not_correct", 
            "label": false
          }, 
          {
            "source": "auto", 
            "detailed-label": "auto_not_correct", 
            "label": false
          }
        ]
      }
    }, 
    {
      "slu-labels": [
        {
          "source": "auto", 
          "slots": {
            "route": "6"
          }, 
          "system-specific": "auto-not-correct", 
          "label": false
        }, 
        {
          "source": "auto", 
          "slots": {
            "route": "5"
          }, 
          "system-specific": "auto-not-correct", 
          "label": false
        }, 
        {
          "source": "auto", 
          "slots": {
            "route": "r"
          }, 
          "system-specific": "auto-not-correct", 
          "label": false
        }, 
        {
          "source": "auto", 
          "slots": {
            "route": "1"
          }, 
          "system-specific": "auto-not-correct", 
          "label": false
        }, 
        {
          "source": "auto", 
          "slots": {
            "route": "p"
          }, 
          "system-specific": "auto-not-correct", 
          "label": false
        }, 
        {
          "source": "auto", 
          "slots": {
            "route": "g"
          }, 
          "system-specific": "auto-not-correct", 
          "label": false
        }, 
        {
          "source": "auto", 
          "slots": {
            "route": "bm"
          }, 
          "system-specific": "auto-not-correct", 
          "label": false
        }, 
        {
          "source": "auto", 
          "slots": {
            "route": "20"
          }, 
          "system-specific": "auto-not-correct", 
          "label": false
        }
      ], 
      "transcription-status": "no-speech-for-system", 
      "audio-file": "021.raw", 
      "turn-index": 11, 
      "system-specific": {
        "act-labels": [
          {
            "source": "auto", 
            "detailed-label": "auto_not_correct", 
            "label": false
          }, 
          {
            "source": "auto", 
            "detailed-label": "auto_not_correct", 
            "label": false
          }, 
          {
            "source": "auto", 
            "detailed-label": "auto_not_correct", 
            "label": false
          }, 
          {
            "source": "auto", 
            "detailed-label": "auto_not_correct", 
            "label": false
          }, 
          {
            "source": "auto", 
            "detailed-label": "auto_not_correct", 
            "label": false
          }, 
          {
            "source": "auto", 
            "detailed-label": "auto_not_correct", 
            "label": false
          }, 
          {
            "source": "auto", 
            "detailed-label": "auto_not_correct", 
            "label": false
          }, 
          {
            "source": "auto", 
            "detailed-label": "auto_not_correct", 
            "label": false
          }
        ]
      }
    }, 
    {
      "transcription-status": "transcribed", 
      "turn-index": 12, 
      "transcription": "not sure", 
      "audio-file": "024.raw", 
      "system-specific": {
        "act-labels": [
          {
            "source": "human", 
            "detailed-label": "not_correct", 
            "label": false
          }, 
          {
            "source": "human", 
            "detailed-label": "not_correct", 
            "label": false
          }, 
          {
            "source": "human", 
            "detailed-label": "not_correct", 
            "label": false
          }, 
          {
            "source": "human", 
            "detailed-label": "not_correct", 
            "label": false
          }, 
          {
            "source": "human", 
            "detailed-label": "not_correct", 
            "label": false
          }, 
          {
            "source": "human", 
            "detailed-label": "not_correct", 
            "label": false
          }, 
          {
            "source": "human", 
            "detailed-label": "not_correct", 
            "label": false
          }, 
          {
            "source": "human", 
            "detailed-label": "not_correct", 
            "label": false
          }, 
          {
            "source": "human", 
            "detailed-label": "not_correct", 
            "label": false
          }, 
          {
            "source": "human", 
            "detailed-label": "not_correct", 
            "label": false
          }
        ]
      }, 
      "slu-labels": [
        {
          "source": "human", 
          "slots": {
            "route": "6"
          }, 
          "system-specific": "not-correct", 
          "label": false
        }, 
        {
          "source": "human", 
          "slots": {
            "route": "r"
          }, 
          "system-specific": "not-correct", 
          "label": false
        }, 
        {
          "source": "human", 
          "slots": {
            "route": "1"
          }, 
          "system-specific": "not-correct", 
          "label": false
        }, 
        {
          "source": "human", 
          "slots": {
            "route": "p"
          }, 
          "system-specific": "not-correct", 
          "label": false
        }, 
        {
          "source": "human", 
          "slots": {
            "route": "60"
          }, 
          "system-specific": "not-correct", 
          "label": false
        }, 
        {
          "source": "human", 
          "slots": {
            "route": "pg"
          }, 
          "system-specific": "not-correct", 
          "label": false
        }, 
        {
          "source": "human", 
          "slots": {
            "route": "g"
          }, 
          "system-specific": "not-correct", 
          "label": false
        }, 
        {
          "source": "human", 
          "slots": {
            "route": "ml"
          }, 
          "system-specific": "not-correct", 
          "label": false
        }, 
        {
          "source": "human", 
          "slots": {
            "route": "g3"
          }, 
          "system-specific": "not-correct", 
          "label": false
        }
      ]
    }, 
    {
      "transcription-status": "transcribed", 
      "turn-index": 13, 
      "transcription": "i'm not sure", 
      "audio-file": "025.raw", 
      "system-specific": {
        "act-labels": [
          {
            "source": "auto", 
            "detailed-label": "auto_not_correct", 
            "label": false
          }, 
          {
            "source": "auto", 
            "detailed-label": "exact_match", 
            "label": true
          }, 
          {
            "source": "auto", 
            "detailed-label": "auto_not_correct", 
            "label": false
          }, 
          {
            "source": "auto", 
            "detailed-label": "auto_not_correct", 
            "label": false
          }, 
          {
            "source": "auto", 
            "detailed-label": "auto_not_correct", 
            "label": false
          }, 
          {
            "source": "auto", 
            "detailed-label": "auto_not_correct", 
            "label": false
          }, 
          {
            "source": "auto", 
            "detailed-label": "auto_not_correct", 
            "label": false
          }, 
          {
            "source": "auto", 
            "detailed-label": "auto_not_correct", 
            "label": false
          }, 
          {
            "source": "auto", 
            "detailed-label": "auto_not_correct", 
            "label": false
          }, 
          {
            "source": "auto", 
            "detailed-label": "auto_not_correct", 
            "label": false
          }, 
          {
            "source": "auto", 
            "detailed-label": "auto_not_correct", 
            "label": false
          }, 
          {
            "source": "auto", 
            "detailed-label": "auto_not_correct", 
            "label": false
          }, 
          {
            "source": "auto", 
            "detailed-label": "auto_not_correct", 
            "label": false
          }, 
          {
            "source": "auto", 
            "detailed-label": "auto_not_correct", 
            "label": false
          }
        ]
      }, 
      "slu-labels": [
        {
          "source": "auto", 
          "slots": {
            "route": "o5"
          }, 
          "system-specific": "auto-not-correct", 
          "label": false
        }, 
        {
          "source": "auto", 
          "slots": {
            "route": "o4"
          }, 
          "system-specific": "auto-not-correct", 
          "label": false
        }, 
        {
          "source": "auto", 
          "slots": {
            "route": "y1"
          }, 
          "system-specific": "auto-not-correct", 
          "label": false
        }, 
        {
          "source": "auto", 
          "slots": {
            "route": "red"
          }, 
          "system-specific": "auto-not-correct", 
          "label": false
        }, 
        {
          "source": "auto", 
          "slots": {
            "route": "r"
          }, 
          "system-specific": "auto-not-correct", 
          "label": false
        }, 
        {
          "source": "auto", 
          "slots": {
            "route": "1"
          }, 
          "system-specific": "auto-not-correct", 
          "label": false
        }, 
        {
          "source": "auto", 
          "slots": {
            "route": "p"
          }, 
          "system-specific": "auto-not-correct", 
          "label": false
        }, 
        {
          "source": "auto", 
          "slots": {
            "route": "dont_know"
          }, 
          "system-specific": "exact-match", 
          "label": true
        }, 
        {
          "source": "auto", 
          "slots": {
            "route": "br"
          }, 
          "system-specific": "auto-not-correct", 
          "label": false
        }, 
        {
          "source": "auto", 
          "slots": {
            "route": "1f"
          }, 
          "system-specific": "auto-not-correct", 
          "label": false
        }, 
        {
          "source": "auto", 
          "slots": {
            "route": "g"
          }, 
          "system-specific": "auto-not-correct", 
          "label": false
        }, 
        {
          "source": "auto", 
          "slots": {
            "route": "ml"
          }, 
          "system-specific": "auto-not-correct", 
          "label": false
        }, 
        {
          "source": "auto", 
          "slots": {
            "route": "g2"
          }, 
          "system-specific": "auto-not-correct", 
          "label": false
        }
      ]
    }, 
    {
      "slu-labels": [
        {
          "source": "auto", 
          "slots": {
            "route": "o5"
          }, 
          "system-specific": "auto-not-correct", 
          "label": false
        }, 
        {
          "source": "auto", 
          "slots": {
            "route": "6"
          }, 
          "system-specific": "auto-not-correct", 
          "label": false
        }, 
        {
          "source": "auto", 
          "slots": {
            "route": "5"
          }, 
          "system-specific": "auto-not-correct", 
          "label": false
        }, 
        {
          "source": "auto", 
          "slots": {
            "route": "r"
          }, 
          "system-specific": "auto-not-correct", 
          "label": false
        }, 
        {
          "source": "auto", 
          "slots": {
            "route": "1"
          }, 
          "system-specific": "auto-not-correct", 
          "label": false
        }, 
        {
          "source": "auto", 
          "slots": {
            "route": "p"
          }, 
          "system-specific": "auto-not-correct", 
          "label": false
        }, 
        {
          "source": "auto", 
          "slots": {
            "route": "g"
          }, 
          "system-specific": "auto-not-correct", 
          "label": false
        }
      ], 
      "transcription-status": "no-speech-for-system", 
      "audio-file": "026.raw", 
      "turn-index": 14, 
      "system-specific": {
        "act-labels": [
          {
            "source": "auto", 
            "detailed-label": "auto_not_correct", 
            "label": false
          }, 
          {
            "source": "auto", 
            "detailed-label": "auto_not_correct", 
            "label": false
          }, 
          {
            "source": "auto", 
            "detailed-label": "auto_not_correct", 
            "label": false
          }, 
          {
            "source": "auto", 
            "detailed-label": "auto_not_correct", 
            "label": false
          }, 
          {
            "source": "auto", 
            "detailed-label": "auto_not_correct", 
            "label": false
          }, 
          {
            "source": "auto", 
            "detailed-label": "auto_not_correct", 
            "label": false
          }, 
          {
            "source": "auto", 
            "detailed-label": "auto_not_correct", 
            "label": false
          }
        ]
      }
    }, 
    {
      "transcription-status": "transcribed", 
      "turn-index": 15, 
      "transcription": "i'm not sure", 
      "audio-file": "029.raw", 
      "system-specific": {
        "act-labels": [
          {
            "source": "auto", 
            "detailed-label": "auto_not_correct", 
            "label": false
          }, 
          {
            "source": "auto", 
            "detailed-label": "auto_not_correct", 
            "label": false
          }, 
          {
            "source": "auto", 
            "detailed-label": "auto_correct", 
            "label": true
          }, 
          {
            "source": "auto", 
            "detailed-label": "auto_not_correct", 
            "label": false
          }, 
          {
            "source": "auto", 
            "detailed-label": "auto_not_correct", 
            "label": false
          }, 
          {
            "source": "auto", 
            "detailed-label": "auto_not_correct", 
            "label": false
          }, 
          {
            "source": "auto", 
            "detailed-label": "auto_not_correct", 
            "label": false
          }, 
          {
            "source": "auto", 
            "detailed-label": "auto_not_correct", 
            "label": false
          }, 
          {
            "source": "auto", 
            "detailed-label": "auto_not_correct", 
            "label": false
          }, 
          {
            "source": "auto", 
            "detailed-label": "auto_not_correct", 
            "label": false
          }, 
          {
            "source": "auto", 
            "detailed-label": "auto_not_correct", 
            "label": false
          }, 
          {
            "source": "auto", 
            "detailed-label": "auto_not_correct", 
            "label": false
          }, 
          {
            "source": "auto", 
            "detailed-label": "auto_not_correct", 
            "label": false
          }, 
          {
            "source": "auto", 
            "detailed-label": "auto_not_correct", 
            "label": false
          }
        ]
      }, 
      "slu-labels": [
        {
          "source": "auto", 
          "slots": {
            "route": "6"
          }, 
          "system-specific": "auto-not-correct", 
          "label": false
        }, 
        {
          "source": "auto", 
          "slots": {
            "route": "r"
          }, 
          "system-specific": "auto-not-correct", 
          "label": false
        }, 
        {
          "source": "auto", 
          "slots": {
            "route": "1"
          }, 
          "system-specific": "auto-not-correct", 
          "label": false
        }, 
        {
          "source": "auto", 
          "slots": {
            "route": "p"
          }, 
          "system-specific": "auto-not-correct", 
          "label": false
        }, 
        {
          "source": "auto", 
          "slots": {
            "route": "dont_know"
          }, 
          "system-specific": "auto-correct", 
          "label": true
        }, 
        {
          "source": "auto", 
          "slots": {
            "route": "gc"
          }, 
          "system-specific": "auto-not-correct", 
          "label": false
        }, 
        {
          "source": "auto", 
          "slots": {
            "route": "g"
          }, 
          "system-specific": "auto-not-correct", 
          "label": false
        }, 
        {
          "source": "auto", 
          "slots": {
            "route": "ml"
          }, 
          "system-specific": "auto-not-correct", 
          "label": false
        }, 
        {
          "source": "auto", 
          "slots": {
            "route": "6c"
          }, 
          "system-specific": "auto-not-correct", 
          "label": false
        }, 
        {
          "source": "auto", 
          "slots": {
            "route": "6a"
          }, 
          "system-specific": "auto-not-correct", 
          "label": false
        }, 
        {
          "source": "auto", 
          "slots": {
            "route": "60"
          }, 
          "system-specific": "auto-not-correct", 
          "label": false
        }, 
        {
          "source": "auto", 
          "slots": {
            "route": "6d"
          }, 
          "system-specific": "auto-not-correct", 
          "label": false
        }
      ]
    }, 
    {
      "slu-labels": [
        {
          "source": "auto", 
          "slots": {
            "route": "6"
          }, 
          "system-specific": "auto-not-correct", 
          "label": false
        }, 
        {
          "source": "auto", 
          "slots": {
            "route": "r"
          }, 
          "system-specific": "auto-not-correct", 
          "label": false
        }, 
        {
          "source": "auto", 
          "slots": {
            "route": "1"
          }, 
          "system-specific": "auto-not-correct", 
          "label": false
        }, 
        {
          "source": "auto", 
          "slots": {
            "route": "p"
          }, 
          "system-specific": "auto-not-correct", 
          "label": false
        }, 
        {
          "source": "auto", 
          "slots": {
            "route": "p10"
          }, 
          "system-specific": "auto-not-correct", 
          "label": false
        }, 
        {
          "source": "auto", 
          "slots": {
            "route": "bm"
          }, 
          "system-specific": "auto-not-correct", 
          "label": false
        }, 
        {
          "source": "auto", 
          "slots": {
            "route": "pg"
          }, 
          "system-specific": "auto-not-correct", 
          "label": false
        }, 
        {
          "source": "auto", 
          "slots": {
            "route": "g"
          }, 
          "system-specific": "auto-not-correct", 
          "label": false
        }, 
        {
          "source": "auto", 
          "slots": {
            "route": "ml"
          }, 
          "system-specific": "auto-not-correct", 
          "label": false
        }, 
        {
          "source": "auto", 
          "slots": {
            "route": "18"
          }, 
          "system-specific": "auto-not-correct", 
          "label": false
        }, 
        {
          "source": "auto", 
          "slots": {
            "route": "g2"
          }, 
          "system-specific": "auto-not-correct", 
          "label": false
        }
      ], 
      "transcription-status": "not-understandable", 
      "audio-file": "032.raw", 
      "turn-index": 16, 
      "system-specific": {
        "act-labels": [
          {
            "source": "auto", 
            "detailed-label": "auto_not_correct", 
            "label": false
          }, 
          {
            "source": "auto", 
            "detailed-label": "auto_not_correct", 
            "label": false
          }, 
          {
            "source": "auto", 
            "detailed-label": "auto_not_correct", 
            "label": false
          }, 
          {
            "source": "auto", 
            "detailed-label": "auto_not_correct", 
            "label": false
          }, 
          {
            "source": "auto", 
            "detailed-label": "auto_not_correct", 
            "label": false
          }, 
          {
            "source": "auto", 
            "detailed-label": "auto_not_correct", 
            "label": false
          }, 
          {
            "source": "auto", 
            "detailed-label": "auto_not_correct", 
            "label": false
          }, 
          {
            "source": "auto", 
            "detailed-label": "auto_not_correct", 
            "label": false
          }, 
          {
            "source": "auto", 
            "detailed-label": "auto_not_correct", 
            "label": false
          }, 
          {
            "source": "auto", 
            "detailed-label": "auto_not_correct", 
            "label": false
          }, 
          {
            "source": "auto", 
            "detailed-label": "auto_not_correct", 
            "label": false
          }, 
          {
            "source": "auto", 
            "detailed-label": "auto_not_correct", 
            "label": false
          }, 
          {
            "source": "auto", 
            "detailed-label": "auto_not_correct", 
            "label": false
          }
        ]
      }
    }, 
    {
      "slu-labels": [
        {
          "source": "auto", 
          "slots": {
            "route": "6"
          }, 
          "system-specific": "auto-not-correct", 
          "label": false
        }, 
        {
          "source": "auto", 
          "slots": {
            "route": "5"
          }, 
          "system-specific": "auto-not-correct", 
          "label": false
        }, 
        {
          "source": "auto", 
          "slots": {
            "route": "bm"
          }, 
          "system-specific": "auto-not-correct", 
          "label": false
        }, 
        {
          "source": "auto", 
          "slots": {
            "route": "r"
          }, 
          "system-specific": "auto-not-correct", 
          "label": false
        }, 
        {
          "source": "auto", 
          "slots": {
            "route": "1"
          }, 
          "system-specific": "auto-not-correct", 
          "label": false
        }, 
        {
          "source": "auto", 
          "slots": {
            "route": "p"
          }, 
          "system-specific": "auto-not-correct", 
          "label": false
        }, 
        {
          "source": "auto", 
          "slots": {
            "route": "dont_know"
          }, 
          "system-specific": "auto-not-correct", 
          "label": false
        }, 
        {
          "source": "auto", 
          "slots": {
            "route": "br"
          }, 
          "system-specific": "auto-not-correct", 
          "label": false
        }, 
        {
          "source": "auto", 
          "slots": {
            "route": "y1"
          }, 
          "system-specific": "auto-not-correct", 
          "label": false
        }, 
        {
          "source": "auto", 
          "slots": {
            "route": "1f"
          }, 
          "system-specific": "auto-not-correct", 
          "label": false
        }, 
        {
          "source": "auto", 
          "slots": {
            "route": "g"
          }, 
          "system-specific": "auto-not-correct", 
          "label": false
        }, 
        {
          "source": "auto", 
          "slots": {
            "route": "ml"
          }, 
          "system-specific": "auto-not-correct", 
          "label": false
        }, 
        {
          "source": "auto", 
          "slots": {
            "route": "11"
          }, 
          "system-specific": "auto-not-correct", 
          "label": false
        }, 
        {
          "source": "auto", 
          "slots": {
            "route": "12a"
          }, 
          "system-specific": "auto-not-correct", 
          "label": false
        }
      ], 
      "transcription-status": "not-understandable", 
      "audio-file": "033.raw", 
      "turn-index": 17, 
      "system-specific": {
        "act-labels": [
          {
            "source": "auto", 
            "detailed-label": "auto_not_correct", 
            "label": false
          }, 
          {
            "source": "auto", 
            "detailed-label": "auto_not_correct", 
            "label": false
          }, 
          {
            "source": "auto", 
            "detailed-label": "auto_not_correct", 
            "label": false
          }, 
          {
            "source": "auto", 
            "detailed-label": "auto_not_correct", 
            "label": false
          }, 
          {
            "source": "auto", 
            "detailed-label": "auto_not_correct", 
            "label": false
          }, 
          {
            "source": "auto", 
            "detailed-label": "auto_not_correct", 
            "label": false
          }, 
          {
            "source": "auto", 
            "detailed-label": "auto_not_correct", 
            "label": false
          }, 
          {
            "source": "auto", 
            "detailed-label": "auto_not_correct", 
            "label": false
          }, 
          {
            "source": "auto", 
            "detailed-label": "auto_not_correct", 
            "label": false
          }, 
          {
            "source": "auto", 
            "detailed-label": "auto_not_correct", 
            "label": false
          }, 
          {
            "source": "auto", 
            "detailed-label": "auto_not_correct", 
            "label": false
          }, 
          {
            "source": "auto", 
            "detailed-label": "auto_not_correct", 
            "label": false
          }, 
          {
            "source": "auto", 
            "detailed-label": "auto_not_correct", 
            "label": false
          }, 
          {
            "source": "auto", 
            "detailed-label": "auto_not_correct", 
            "label": false
          }, 
          {
            "source": "auto", 
            "detailed-label": "auto_not_correct", 
            "label": false
          }
        ]
      }
    }, 
    {
      "slu-labels": [], 
      "transcription-status": "audio-not-available", 
      "audio-file": null, 
      "turn-index": 18, 
      "system-specific": {
        "act-labels": []
      }
    }
  ]
}